{
  "Signup": {
    "sidebarBackground": "./sidebar_background.png",
    "logo": "./logo.svg",
    "robotIcon": "./robot_interacting_with_computer.svg",
    "checkmark": "./radial_checkmark.svg",
    "eyeIcon": "./eye_icon.svg"
  },
  "Footer": {
    "locationIcon": "./location_icon.svg",
    "telephoneIcon": "./telephone_icon.svg",
    "emailIcon": "./email_icon.svg",
    "facebookIcon": "./facebook.svg",
    "linkedInIcon": "./linkedIn.svg",
    "twitterIcon": "./twitter.svg",
    "whatsappIcon": "./whatsapp.svg"
  },
  "Sidebar": {
    "dashboard": {
      "black": "./dashboard_icon_black.svg",
      "white": "./dashboard_icon_white.svg"
    },
    "virtualAssistant": {
      "black": "./virtual_assistant_icon_black.svg",
      "white": "./virtual_assistant_icon_white.svg"
    }
  },
  "UserSidebar": {
    "dashboard": {
      "black": "./dashboard_icon_black.svg",
      "white": "./dashboard_icon_white.svg"
    },
    "callHistory": {
      "black": "./call_history_icon_black.svg",
      "white": "./call_history_icon_white.svg"
    },
    "settings": {
      "black": "./settings_icon_black.png",
      "white": "./settings_icon_white.svg"
    },
    "voiceAssistant": {
      "black": "./voice_assistant_icon_black.svg",
      "white": "./voice_assistant_icon_white.svg"
    }
  },
  "Navbar": {
    "searchIcon": "./search_icon.svg",
    "addIcon": "./add_icon.svg",
    "notificationIcon": "./notification_icon.svg",
    "avatarIcon": "./avatar_icon.svg"
  },
  "VirtualAssistantTable": {
    "arrowDownIcon": "./arrow_down_icon.svg",
    "arrowUpIcon": "./arrow_up_icon.svg",
    "editIcon": "./edit_icon.svg",
    "recycleBinIcon": "./recycle_bin_icon.svg"
  },
  "Modal": {
    "icon": "./modal_icon.png"
  },
  "Chat": {
    "clientBackground": "./client_background.png",
    "aiAssistantBackground": "./ai_assistant_background.png",
    "sendIcon": "./send_icon.svg",
    "startIcon": "./start_icon.svg",
    "stopIcon": "./stop_icon.svg"
  }
}
